<?xml version="1.0" encoding="UTF-8"?>
<PermissionSet xmlns="http://soap.sforce.com/2006/04/metadata">
    <fieldPermissions>
        <editable>false</editable>
        <field>sbaa__Approval__c.Quote__c</field>
        <readable>true</readable>
    </fieldPermissions>
    <fieldPermissions>
        <editable>false</editable>
        <field>sbaa__Approval__c.sbaa__Approver__c</field>
        <readable>true</readable>
    </fieldPermissions>
    <fieldPermissions>
        <editable>true</editable>
        <field>sbaa__Approval__c.sbaa__CommentsLong__c</field>
        <readable>true</readable>
    </fieldPermissions>
    <fieldPermissions>
        <editable>false</editable>
        <field>sbaa__Approval__c.sbaa__DelegatedApprover__c</field>
        <readable>true</readable>
    </fieldPermissions>
    <hasActivationRequired>false</hasActivationRequired>
    <label>CPQ Advance Approval Read Permission</label>
    <objectPermissions>
        <allowCreate>false</allowCreate>
        <allowDelete>false</allowDelete>
        <allowEdit>false</allowEdit>
        <allowRead>true</allowRead>
        <modifyAllRecords>false</modifyAllRecords>
        <object>sbaa__ApprovalChain__c</object>
        <viewAllRecords>false</viewAllRecords>
    </objectPermissions>
    <objectPermissions>
        <allowCreate>false</allowCreate>
        <allowDelete>false</allowDelete>
        <allowEdit>false</allowEdit>
        <allowRead>true</allowRead>
        <modifyAllRecords>false</modifyAllRecords>
        <object>sbaa__Approval__c</object>
        <viewAllRecords>false</viewAllRecords>
    </objectPermissions>
    <tabSettings>
        <tab>sbaa__ApprovalChain__c</tab>
        <visibility>Visible</visibility>
    </tabSettings>
</PermissionSet>
