{
  "appPageId" : "538d2fc7-5a95-404e-8a48-8270eddc2666",
  "componentName" : "siteforce:sldsOneColLayout",
  "dataProviders" : [ ],
  "id" : "dfceb4f0-07ab-4b2f-8503-d8058aca0b8e",
  "label" : "Record List",
  "regions" : [ {
    "id" : "0bc64a97-efda-45fb-aaec-0629dfaf844e",
    "regionName" : "header",
    "type" : "region"
  }, {
    "components" : [ {
      "componentAttributes" : {
        "enableInlineEdit" : true,
        "filterName" : "{!filterId}",
        "layout" : "FULL",
        "pageSize" : 25,
        "scope" : "{!objectName}",
        "showActionBar" : true,
        "showChartsPanel" : true,
        "showDisplay" : "showall",
        "showFilterPanel" : true,
        "showImageIcon" : true,
        "showManualRefreshButton" : true,
        "showObjectName" : true,
        "showPinnedList" : true,
        "showSearchBar" : true
      },
      "componentName" : "forceCommunity:objectHome",
      "id" : "d5f0e3ee-14b8-492b-99e1-246989fbf55a",
      "renderPriority" : "NEUTRAL",
      "renditionMap" : { },
      "type" : "component"
    } ],
    "id" : "a0e6d796-44c6-4b56-94a7-251e785004ed",
    "regionName" : "content",
    "type" : "region"
  }, {
    "id" : "6c198190-c7f5-4575-8357-ffe3f9acff2f",
    "regionName" : "footer",
    "type" : "region"
  } ],
  "themeLayoutType" : "Inner",
  "type" : "view",
  "viewType" : "list"
}